README.md
setup.cfg
setup.py
src/mysql_utils.py
src/mysql_utils.egg-info/PKG-INFO
src/mysql_utils.egg-info/SOURCES.txt
src/mysql_utils.egg-info/dependency_links.txt
src/mysql_utils.egg-info/requires.txt
src/mysql_utils.egg-info/top_level.txt