Metadata-Version: 1.1
Name: mysql-utils
Version: 0.0.2
Summary: A simple MySQL library including a set of utility APIs for Python database programming
Home-page: https://github.com/slxiao/mysql-utils
Author: Shelwin Xiao
Author-email: shliangxiao@gmail.com
License: Public Domain
Keywords: mysql,API,utility
Platform: UNKNOWN
Classifier: Programming Language :: Python
Classifier: Intended Audience :: Developers
Classifier: License :: Public Domain
Classifier: Operating System :: OS Independent
Classifier: Topic :: Software Development :: Libraries :: Python Modules
